pytest_wdb.py
pytest_wdb-0.4.0.dist-info/METADATA
pytest_wdb-0.4.0.dist-info/RECORD
pytest_wdb-0.4.0.dist-info/WHEEL
pytest_wdb-0.4.0.dist-info/entry_points.txt
pytest_wdb-0.4.0.dist-info/DESCRIPTION.rst
pytest_wdb-0.4.0.dist-info/top_level.txt
pytest_wdb-0.4.0.dist-info/metadata.json
