Metadata-Version: 2.0
Name: pytest-wdb
Version: 0.4.0
Summary: Trace pytest tests with wdb to halt on error with --wdb.
Home-page: http://github.com/Kozea/wdb
Author: Florian Mounier @ kozea
Author-email: florian.mounier@kozea.fr
License: GPLv3
Platform: UNKNOWN
Requires-Dist: wdb
